easy_aoc/__init__.py
easy_aoc/app.py
easy_aoc/client.py
easy_aoc/config.py
easy_aoc/db/__init__.py
easy_aoc/db/models.py
easy_aoc/domain.py
easy_aoc/exceptions.py
easy_aoc/puzzle.py
easy_aoc/repository/__init__.py
easy_aoc/repository/input_repository.py
easy_aoc/repository/submission_repository.py
easy_aoc/utils.py
easy_aoc/version.py
easy_aoc-0.2.0.dist-info/WHEEL
easy_aoc-0.2.0.dist-info/METADATA
easy_aoc-0.2.0.dist-info/RECORD
