Metadata-Version: 2.1
Name: easy-aoc
Version: 0.2.0
Summary: Tools for the Advent of Code
License: MIT
Author: Sebastiaan Zeeff
Author-email: sebastiaan.zeeff@gmail.nl
Requires-Python: >=3.10,<4.0
Classifier: License :: OSI Approved :: MIT License
Classifier: Programming Language :: Python :: 3
Classifier: Programming Language :: Python :: 3.10
Classifier: Programming Language :: Python :: 3.11
Requires-Dist: appdirs (>=1.4.4,<2.0.0)
Requires-Dist: attrs (>=22.1.0,<23.0.0)
Requires-Dist: beautifulsoup4 (>=4.11.1,<5.0.0)
Requires-Dist: requests (>=2.28.1,<3.0.0)
Requires-Dist: sqlalchemy (>=2.0.0b4,<3.0.0)
Requires-Dist: yarl (>=1.8.2,<2.0.0)
